craigslist_scraper/__init__.py
craigslist_scraper/scraper.py
craigslist_scraper-1.1.0.dist-info/DESCRIPTION.rst
craigslist_scraper-1.1.0.dist-info/METADATA
craigslist_scraper-1.1.0.dist-info/RECORD
craigslist_scraper-1.1.0.dist-info/WHEEL
craigslist_scraper-1.1.0.dist-info/metadata.json
craigslist_scraper-1.1.0.dist-info/top_level.txt
craigslist_scraper-1.1.0.dist-info/zip-safe
tests/__init__.py
tests/test_scraper.py
