Metadata-Version: 2.0
Name: craigslist-scraper
Version: 1.1.0
Summary: Provide information for craigslist related metadata
Home-page: https://github.com/narfman0/craigslist-scraper
Author: Jon Robison
Author-email: narfman0@gmail.com
License: LICENSE
Keywords: craigslist scraper meta
Platform: UNKNOWN
Classifier: Development Status :: 4 - Beta
Classifier: License :: OSI Approved :: GNU General Public License v3 (GPLv3)
Classifier: Operating System :: OS Independent
Classifier: Programming Language :: Python
Classifier: Topic :: Software Development :: Libraries :: Python Modules
Requires-Dist: beautifulsoup4
Requires-Dist: requests
